{
    "ret":true,
    "data":{
        "list":[{
            "id":1001,
            "title":"空中英语教室",
            "link":"/list/1001"
        },
        {
            "id":1002,
            "title":"大家说英语",
            "link":"/list/1002"
        },
        {
            "id":1003,
            "title":"彭蒙惠英语",
            "link":"/list/1003"
        },
        {
            "id":1004,
            "title":"科学美国人",
            "link":"/list/1004"
        },
        {
            "id":1005,
            "title":"东吴相对论",
            "link":"/list/1005"
        },
        {
            "id":1006,
            "title":"走遍美国",
            "link":"/list/1006"
        },
        {
            "id":1007,
            "title":"英文名著",
            "link":"/list/1007"
        },
        {
            "id":1008,
            "title":"托福考试",
            "link":"/list/1008"
        },
        {
            "id":1009,
            "title":"美国脱口秀",
            "link":"/list/1009"
        },
        {
            "id":1010,
            "title":"BBC听力资料",
            "link":"/list/1010"
        }
        ,
        {
            "id":1011,
            "title":"外教课堂",
            "link":"/list/1011"
        }
    ]
    }
}